README.md
setup.py
qscache/__init__.py
qscache/manage.py
qscache.egg-info/PKG-INFO
qscache.egg-info/SOURCES.txt
qscache.egg-info/dependency_links.txt
qscache.egg-info/requires.txt
qscache.egg-info/top_level.txt
qscache/cache/__init__.py
qscache/cache/base.py
qscache/cache/decorators.py
qscache/config/__init__.py
qscache/config/asgi.py
qscache/config/settings.py
qscache/config/urls.py
qscache/config/wsgi.py
qscache/example_app/__init__.py
qscache/example_app/admin.py
qscache/example_app/apps.py
qscache/example_app/cache.py
qscache/example_app/models.py
qscache/example_app/migrations/0001_initial.py
qscache/example_app/migrations/__init__.py
qscache/tests/__init__.py
qscache/tests/test_cache.py